[
  {
    "departureTerminalId": "010",
    "arrivalTerminalId": "850",
    "durationInMinutes": [
      130
    ],
    "operator": [
      "(주)대원고속",
      "(주)천일고속",
      "(주)한일고속"
    ],
    "busClass": [
      "우등"
    ],
    "departureTime": {
      "hour": 6,
      "minute": 50
    },
    "isTemporaryRoute": false,
    "seatsAmount": [
      28
    ],
    "fare": {
      "어른": [
        19000
      ],
      "초등생": [
        9500
      ],
      "중고생": [
        0
      ]
    },
    "pattern": {
      "type": "irregular",
      "fixedDays": [
        1,
        2,
        3,
        4,
        5,
        7
      ],
      "irregularDays": [
        6
      ]
    }
  },
  {
    "departureTerminalId": "010",
    "arrivalTerminalId": "850",
    "durationInMinutes": [
      130
    ],
    "operator": [
      "(주)대원고속",
      "(주)천일고속",
      "(주)한일고속"
    ],
    "busClass": [
      "고속"
    ],
    "departureTime": {
      "hour": 8,
      "minute": 0
    },
    "isTemporaryRoute": false,
    "seatsAmount": [
      28
    ],
    "fare": {
      "어른": [
        13000
      ],
      "초등생": [
        6500
      ],
      "중고생": [
        10400
      ]
    },
    "pattern": {
      "type": "everyday"
    }
  },
  {
    "departureTerminalId": "010",
    "arrivalTerminalId": "850",
    "durationInMinutes": [
      130
    ],
    "operator": [
      "(주)대원고속",
      "(주)천일고속",
      "(주)한일고속"
    ],
    "busClass": [
      "우등"
    ],
    "departureTime": {
      "hour": 9,
      "minute": 10
    },
    "isTemporaryRoute": false,
    "seatsAmount": [
      28
    ],
    "fare": {
      "어른": [
        19000
      ],
      "초등생": [
        9500
      ],
      "중고생": [
        0
      ]
    },
    "pattern": {
      "type": "everyday"
    }
  },
  {
    "departureTerminalId": "010",
    "arrivalTerminalId": "850",
    "durationInMinutes": [
      130
    ],
    "operator": [
      "(주)대원고속",
      "(주)천일고속",
      "(주)한일고속"
    ],
    "busClass": [
      "우등"
    ],
    "departureTime": {
      "hour": 10,
      "minute": 20
    },
    "isTemporaryRoute": false,
    "seatsAmount": [
      28
    ],
    "fare": {
      "어른": [
        19000
      ],
      "초등생": [
        9500
      ],
      "중고생": [
        0
      ]
    },
    "pattern": {
      "type": "everyday"
    }
  },
  {
    "departureTerminalId": "010",
    "arrivalTerminalId": "850",
    "durationInMinutes": [
      130
    ],
    "operator": [
      "(주)대원고속",
      "(주)천일고속",
      "(주)한일고속"
    ],
    "busClass": [
      "고속"
    ],
    "departureTime": {
      "hour": 11,
      "minute": 40
    },
    "isTemporaryRoute": false,
    "seatsAmount": [
      28
    ],
    "fare": {
      "어른": [
        13000
      ],
      "초등생": [
        6500
      ],
      "중고생": [
        10400
      ]
    },
    "pattern": {
      "type": "everyday"
    }
  },
  {
    "departureTerminalId": "010",
    "arrivalTerminalId": "850",
    "durationInMinutes": [
      130
    ],
    "operator": [
      "(주)대원고속",
      "(주)천일고속",
      "(주)한일고속"
    ],
    "busClass": [
      "우등"
    ],
    "departureTime": {
      "hour": 12,
      "minute": 40
    },
    "isTemporaryRoute": false,
    "seatsAmount": [
      28
    ],
    "fare": {
      "어른": [
        19000
      ],
      "초등생": [
        9500
      ],
      "중고생": [
        0
      ]
    },
    "pattern": {
      "type": "everyday"
    }
  },
  {
    "departureTerminalId": "010",
    "arrivalTerminalId": "850",
    "durationInMinutes": [
      130
    ],
    "operator": [
      "(주)대원고속",
      "(주)천일고속",
      "(주)한일고속"
    ],
    "busClass": [
      "우등"
    ],
    "departureTime": {
      "hour": 13,
      "minute": 40
    },
    "isTemporaryRoute": false,
    "seatsAmount": [
      28
    ],
    "fare": {
      "어른": [
        19000
      ],
      "초등생": [
        9500
      ],
      "중고생": [
        0
      ]
    },
    "pattern": {
      "type": "everyday"
    }
  },
  {
    "departureTerminalId": "010",
    "arrivalTerminalId": "850",
    "durationInMinutes": [
      130
    ],
    "operator": [
      "(주)대원고속",
      "(주)천일고속",
      "(주)한일고속"
    ],
    "busClass": [
      "고속"
    ],
    "departureTime": {
      "hour": 15,
      "minute": 0
    },
    "isTemporaryRoute": false,
    "seatsAmount": [
      28
    ],
    "fare": {
      "어른": [
        13000
      ],
      "초등생": [
        6500
      ],
      "중고생": [
        10400
      ]
    },
    "pattern": {
      "type": "everyday"
    }
  },
  {
    "departureTerminalId": "010",
    "arrivalTerminalId": "850",
    "durationInMinutes": [
      130
    ],
    "operator": [
      "(주)대원고속",
      "(주)천일고속",
      "(주)한일고속"
    ],
    "busClass": [
      "우등"
    ],
    "departureTime": {
      "hour": 16,
      "minute": 10
    },
    "isTemporaryRoute": false,
    "seatsAmount": [
      28
    ],
    "fare": {
      "어른": [
        19000
      ],
      "초등생": [
        9500
      ],
      "중고생": [
        0
      ]
    },
    "pattern": {
      "type": "everyday"
    }
  },
  {
    "departureTerminalId": "010",
    "arrivalTerminalId": "850",
    "durationInMinutes": [
      130
    ],
    "operator": [
      "(주)대원고속",
      "(주)천일고속",
      "(주)한일고속"
    ],
    "busClass": [
      "우등"
    ],
    "departureTime": {
      "hour": 17,
      "minute": 30
    },
    "isTemporaryRoute": false,
    "seatsAmount": [
      28
    ],
    "fare": {
      "어른": [
        19000
      ],
      "초등생": [
        9500
      ],
      "중고생": [
        0
      ]
    },
    "pattern": {
      "type": "everyday"
    }
  },
  {
    "departureTerminalId": "010",
    "arrivalTerminalId": "850",
    "durationInMinutes": [
      130
    ],
    "operator": [
      "(주)대원고속",
      "(주)천일고속",
      "(주)한일고속"
    ],
    "busClass": [
      "고속"
    ],
    "departureTime": {
      "hour": 18,
      "minute": 50
    },
    "isTemporaryRoute": false,
    "seatsAmount": [
      28
    ],
    "fare": {
      "어른": [
        13000
      ],
      "초등생": [
        6500
      ],
      "중고생": [
        10400
      ]
    },
    "pattern": {
      "type": "everyday"
    }
  },
  {
    "departureTerminalId": "010",
    "arrivalTerminalId": "850",
    "durationInMinutes": [
      130
    ],
    "operator": [
      "(주)대원고속",
      "(주)천일고속",
      "(주)한일고속"
    ],
    "busClass": [
      "우등"
    ],
    "departureTime": {
      "hour": 20,
      "minute": 20
    },
    "isTemporaryRoute": false,
    "seatsAmount": [
      28
    ],
    "fare": {
      "어른": [
        19000
      ],
      "초등생": [
        9500
      ],
      "중고생": [
        0
      ]
    },
    "pattern": {
      "type": "everyday"
    }
  }
]