[
  {
    "departureTerminalId": "622",
    "arrivalTerminalId": "021",
    "durationInMinutes": [
      170
    ],
    "operator": [
      "금호익스프레스(주)"
    ],
    "busClass": [
      "우등"
    ],
    "departureTime": {
      "hour": 6,
      "minute": 55
    },
    "isTemporaryRoute": false,
    "seatsAmount": [
      28
    ],
    "fare": {
      "어른": [
        21900
      ],
      "초등생": [
        11000
      ],
      "중고생": [
        17500
      ]
    },
    "pattern": {
      "type": "everyday"
    }
  },
  {
    "departureTerminalId": "622",
    "arrivalTerminalId": "021",
    "durationInMinutes": [
      170
    ],
    "operator": [
      "금호익스프레스(주)"
    ],
    "busClass": [
      "우등"
    ],
    "departureTime": {
      "hour": 11,
      "minute": 55
    },
    "isTemporaryRoute": false,
    "seatsAmount": [
      28
    ],
    "fare": {
      "어른": [
        21900
      ],
      "초등생": [
        11000
      ],
      "중고생": [
        17500
      ]
    },
    "pattern": {
      "type": "everyday"
    }
  },
  {
    "departureTerminalId": "622",
    "arrivalTerminalId": "021",
    "durationInMinutes": [
      170
    ],
    "operator": [
      "금호익스프레스(주)"
    ],
    "busClass": [
      "우등"
    ],
    "departureTime": {
      "hour": 18,
      "minute": 55
    },
    "isTemporaryRoute": false,
    "seatsAmount": [
      28
    ],
    "fare": {
      "어른": [
        21900
      ],
      "초등생": [
        11000
      ],
      "중고생": [
        17500
      ]
    },
    "pattern": {
      "type": "even-odd"
    }
  },
  {
    "departureTerminalId": "622",
    "arrivalTerminalId": "021",
    "durationInMinutes": [
      170
    ],
    "operator": [
      "금호익스프레스(주)"
    ],
    "busClass": [
      "우등"
    ],
    "departureTime": {
      "hour": 19,
      "minute": 25
    },
    "isTemporaryRoute": false,
    "seatsAmount": [
      28
    ],
    "fare": {
      "어른": [
        21900
      ],
      "초등생": [
        11000
      ],
      "중고생": [
        17500
      ]
    },
    "pattern": {
      "type": "irregular",
      "fixedDays": [],
      "irregularDays": [
        5,
        6,
        7
      ]
    }
  }
]