[
  {
    "departureTerminalId": "710",
    "arrivalTerminalId": "530",
    "durationInMinutes": [
      215
    ],
    "operator": [
      "금호익스프레스(주)"
    ],
    "busClass": [
      "우등"
    ],
    "departureTime": {
      "hour": 8,
      "minute": 0
    },
    "isTemporaryRoute": false,
    "seatsAmount": [
      28
    ],
    "fare": {
      "어른": [
        30000
      ],
      "초등생": [
        15000
      ],
      "중고생": [
        24000
      ]
    },
    "pattern": {
      "type": "everyday"
    }
  },
  {
    "departureTerminalId": "710",
    "arrivalTerminalId": "530",
    "durationInMinutes": [
      215
    ],
    "operator": [
      "금호익스프레스(주)"
    ],
    "busClass": [
      "우등"
    ],
    "departureTime": {
      "hour": 16,
      "minute": 30
    },
    "isTemporaryRoute": false,
    "seatsAmount": [
      28
    ],
    "fare": {
      "어른": [
        30000
      ],
      "초등생": [
        15000
      ],
      "중고생": [
        24000
      ]
    },
    "pattern": {
      "type": "everyday"
    }
  }
]