[
  {
    "departureTerminalId": "201",
    "arrivalTerminalId": "010",
    "durationInMinutes": [
      190
    ],
    "operator": [
      "(주)동부고속"
    ],
    "busClass": [
      "우등"
    ],
    "departureTime": {
      "hour": 11,
      "minute": 40
    },
    "isTemporaryRoute": false,
    "seatsAmount": [
      28
    ],
    "fare": {
      "어른": [
        25200
      ],
      "초등생": [
        12600
      ],
      "중고생": [
        20200
      ]
    },
    "pattern": {
      "type": "everyday"
    }
  },
  {
    "departureTerminalId": "201",
    "arrivalTerminalId": "010",
    "durationInMinutes": [
      190
    ],
    "operator": [
      "(주)동부고속"
    ],
    "busClass": [
      "우등"
    ],
    "departureTime": {
      "hour": 13,
      "minute": 40
    },
    "isTemporaryRoute": false,
    "seatsAmount": [
      28
    ],
    "fare": {
      "어른": [
        25200
      ],
      "초등생": [
        12600
      ],
      "중고생": [
        20200
      ]
    },
    "pattern": {
      "type": "everyday"
    }
  },
  {
    "departureTerminalId": "201",
    "arrivalTerminalId": "010",
    "durationInMinutes": [
      190
    ],
    "operator": [
      "(주)동부고속"
    ],
    "busClass": [
      "우등"
    ],
    "departureTime": {
      "hour": 15,
      "minute": 0
    },
    "isTemporaryRoute": false,
    "seatsAmount": [
      28
    ],
    "fare": {
      "어른": [
        25200
      ],
      "초등생": [
        12600
      ],
      "중고생": [
        20200
      ]
    },
    "pattern": {
      "type": "everyday"
    }
  },
  {
    "departureTerminalId": "201",
    "arrivalTerminalId": "010",
    "durationInMinutes": [
      190
    ],
    "operator": [
      "(주)동부고속"
    ],
    "busClass": [
      "우등"
    ],
    "departureTime": {
      "hour": 16,
      "minute": 40
    },
    "isTemporaryRoute": false,
    "seatsAmount": [
      28
    ],
    "fare": {
      "어른": [
        25200
      ],
      "초등생": [
        12600
      ],
      "중고생": [
        20200
      ]
    },
    "pattern": {
      "type": "everyday"
    }
  }
]