[
  {
    "departureTerminalId": "550",
    "arrivalTerminalId": "560",
    "durationInMinutes": [
      50
    ],
    "operator": [
      "금호익스프레스(주)"
    ],
    "busClass": [
      "우등"
    ],
    "departureTime": {
      "hour": 8,
      "minute": 0
    },
    "isTemporaryRoute": false,
    "seatsAmount": [
      28
    ],
    "fare": {
      "어른": [
        0
      ],
      "초등생": [
        0
      ],
      "중고생": [
        0
      ]
    },
    "pattern": {
      "type": "everyday"
    }
  },
  {
    "departureTerminalId": "550",
    "arrivalTerminalId": "560",
    "durationInMinutes": [
      50
    ],
    "operator": [
      "금호익스프레스(주)"
    ],
    "busClass": [
      "우등"
    ],
    "departureTime": {
      "hour": 11,
      "minute": 20
    },
    "isTemporaryRoute": false,
    "seatsAmount": [
      28
    ],
    "fare": {
      "어른": [
        0
      ],
      "초등생": [
        0
      ],
      "중고생": [
        0
      ]
    },
    "pattern": {
      "type": "everyday"
    }
  },
  {
    "departureTerminalId": "550",
    "arrivalTerminalId": "560",
    "durationInMinutes": [
      50
    ],
    "operator": [
      "금호익스프레스(주)"
    ],
    "busClass": [
      "우등"
    ],
    "departureTime": {
      "hour": 16,
      "minute": 35
    },
    "isTemporaryRoute": false,
    "seatsAmount": [
      28
    ],
    "fare": {
      "어른": [
        0
      ],
      "초등생": [
        0
      ],
      "중고생": [
        0
      ]
    },
    "pattern": {
      "type": "everyday"
    }
  }
]