[
  {
    "departureTerminalId": "t-2401401",
    "arrivalTerminalId": "t-2443102"
  },
  {
    "departureTerminalId": "t-2401401",
    "arrivalTerminalId": "t-2420013"
  },
  {
    "departureTerminalId": "t-2401401",
    "arrivalTerminalId": "t-1116401"
  },
  {
    "departureTerminalId": "t-2401401",
    "arrivalTerminalId": "t-1242001"
  },
  {
    "departureTerminalId": "t-2401401",
    "arrivalTerminalId": "t-2446301"
  },
  {
    "departureTerminalId": "t-2401401",
    "arrivalTerminalId": "t-2410001"
  },
  {
    "departureTerminalId": "t-2401401",
    "arrivalTerminalId": "t-1045001"
  },
  {
    "departureTerminalId": "t-2401401",
    "arrivalTerminalId": "t-2465801"
  },
  {
    "departureTerminalId": "t-2401401",
    "arrivalTerminalId": "t-1119201"
  },
  {
    "departureTerminalId": "t-2401401",
    "arrivalTerminalId": "t-0619501"
  },
  {
    "departureTerminalId": "t-2401401",
    "arrivalTerminalId": "t-2420010"
  },
  {
    "departureTerminalId": "t-2401401",
    "arrivalTerminalId": "t-2410401"
  },
  {
    "departureTerminalId": "t-2401401",
    "arrivalTerminalId": "t-2446503"
  },
  {
    "departureTerminalId": "t-2401401",
    "arrivalTerminalId": "t-0499101"
  },
  {
    "departureTerminalId": "t-2401401",
    "arrivalTerminalId": "t-3455101"
  },
  {
    "departureTerminalId": "t-2401401",
    "arrivalTerminalId": "t-1115901"
  },
  {
    "departureTerminalId": "t-2401401",
    "arrivalTerminalId": "t-2446201"
  },
  {
    "departureTerminalId": "t-2401401",
    "arrivalTerminalId": "t-1244601"
  },
  {
    "departureTerminalId": "t-2401401",
    "arrivalTerminalId": "t-0134901"
  },
  {
    "departureTerminalId": "t-2401401",
    "arrivalTerminalId": "t-0511601"
  },
  {
    "departureTerminalId": "t-2401401",
    "arrivalTerminalId": "t-1113901"
  },
  {
    "departureTerminalId": "t-2401401",
    "arrivalTerminalId": "t-2414801"
  },
  {
    "departureTerminalId": "t-2401401",
    "arrivalTerminalId": "t-1110701"
  },
  {
    "departureTerminalId": "t-2401401",
    "arrivalTerminalId": "t-2403201"
  },
  {
    "departureTerminalId": "t-2401401",
    "arrivalTerminalId": "t-1244001"
  },
  {
    "departureTerminalId": "t-2401401",
    "arrivalTerminalId": "t-1403901"
  },
  {
    "departureTerminalId": "t-2401401",
    "arrivalTerminalId": "t-2410702"
  },
  {
    "departureTerminalId": "t-2401401",
    "arrivalTerminalId": "t-2410701"
  },
  {
    "departureTerminalId": "t-2401401",
    "arrivalTerminalId": "t-2415401"
  },
  {
    "departureTerminalId": "t-2401401",
    "arrivalTerminalId": "t-1740701"
  },
  {
    "departureTerminalId": "t-2401401",
    "arrivalTerminalId": "t-2402601"
  },
  {
    "departureTerminalId": "t-2401401",
    "arrivalTerminalId": "t-1640501"
  },
  {
    "departureTerminalId": "t-2401401",
    "arrivalTerminalId": "t-0654501"
  },
  {
    "departureTerminalId": "t-2401401",
    "arrivalTerminalId": "t-2446402"
  },
  {
    "departureTerminalId": "t-2401401",
    "arrivalTerminalId": "t-2446401"
  },
  {
    "departureTerminalId": "t-2401401",
    "arrivalTerminalId": "t-1118801"
  },
  {
    "departureTerminalId": "t-2401401",
    "arrivalTerminalId": "t-1112702"
  },
  {
    "departureTerminalId": "t-2401401",
    "arrivalTerminalId": "t-1149601"
  },
  {
    "departureTerminalId": "t-2401401",
    "arrivalTerminalId": "t-0654601"
  },
  {
    "departureTerminalId": "t-2401401",
    "arrivalTerminalId": "t-1116901"
  },
  {
    "departureTerminalId": "t-2401401",
    "arrivalTerminalId": "t-1110207"
  },
  {
    "departureTerminalId": "t-2401401",
    "arrivalTerminalId": "t-0170401"
  },
  {
    "departureTerminalId": "t-2401401",
    "arrivalTerminalId": "t-1658501"
  },
  {
    "departureTerminalId": "t-2401401",
    "arrivalTerminalId": "t-0101101"
  },
  {
    "departureTerminalId": "t-2401401",
    "arrivalTerminalId": "t-2420701"
  },
  {
    "departureTerminalId": "t-2401401",
    "arrivalTerminalId": "t-1113701"
  },
  {
    "departureTerminalId": "t-2401401",
    "arrivalTerminalId": "t-2406201"
  },
  {
    "departureTerminalId": "t-2401401",
    "arrivalTerminalId": "t-1113001"
  },
  {
    "departureTerminalId": "t-2401401",
    "arrivalTerminalId": "t-2404201"
  },
  {
    "departureTerminalId": "t-2401401",
    "arrivalTerminalId": "t-2420001"
  },
  {
    "departureTerminalId": "t-2401401",
    "arrivalTerminalId": "t-2446302"
  },
  {
    "departureTerminalId": "t-2401401",
    "arrivalTerminalId": "t-1529901"
  },
  {
    "departureTerminalId": "t-2401401",
    "arrivalTerminalId": "t-1400601"
  },
  {
    "departureTerminalId": "t-2401401",
    "arrivalTerminalId": "t-1110902"
  },
  {
    "departureTerminalId": "t-2401401",
    "arrivalTerminalId": "t-1110903"
  },
  {
    "departureTerminalId": "t-2401401",
    "arrivalTerminalId": "t-1110901"
  },
  {
    "departureTerminalId": "t-2401401",
    "arrivalTerminalId": "t-1112901"
  },
  {
    "departureTerminalId": "t-2401401",
    "arrivalTerminalId": "t-2420002"
  },
  {
    "departureTerminalId": "t-2401401",
    "arrivalTerminalId": "t-1244401"
  },
  {
    "departureTerminalId": "t-2401401",
    "arrivalTerminalId": "t-1110601"
  },
  {
    "departureTerminalId": "t-2401401",
    "arrivalTerminalId": "t-2420008"
  },
  {
    "departureTerminalId": "t-2401401",
    "arrivalTerminalId": "t-2420007"
  },
  {
    "departureTerminalId": "t-2401401",
    "arrivalTerminalId": "t-2405901"
  },
  {
    "departureTerminalId": "t-2401401",
    "arrivalTerminalId": "t-1260003"
  },
  {
    "departureTerminalId": "t-2401401",
    "arrivalTerminalId": "t-1624001"
  },
  {
    "departureTerminalId": "t-2401401",
    "arrivalTerminalId": "t-2420004"
  },
  {
    "departureTerminalId": "t-2401401",
    "arrivalTerminalId": "t-1112201"
  },
  {
    "departureTerminalId": "t-2401401",
    "arrivalTerminalId": "t-2406401"
  },
  {
    "departureTerminalId": "t-2401401",
    "arrivalTerminalId": "t-1110202"
  },
  {
    "departureTerminalId": "t-2401401",
    "arrivalTerminalId": "t-1244101"
  },
  {
    "departureTerminalId": "t-2401401",
    "arrivalTerminalId": "t-1174901"
  },
  {
    "departureTerminalId": "t-2401401",
    "arrivalTerminalId": "t-1651001"
  },
  {
    "departureTerminalId": "t-2401401",
    "arrivalTerminalId": "t-2224201"
  },
  {
    "departureTerminalId": "t-2401401",
    "arrivalTerminalId": "t-1111601"
  },
  {
    "departureTerminalId": "t-2401401",
    "arrivalTerminalId": "t-1244701"
  },
  {
    "departureTerminalId": "t-2401401",
    "arrivalTerminalId": "t-2406501"
  },
  {
    "departureTerminalId": "t-2401401",
    "arrivalTerminalId": "t-1172001"
  },
  {
    "departureTerminalId": "t-2401401",
    "arrivalTerminalId": "t-1201301"
  },
  {
    "departureTerminalId": "t-2401401",
    "arrivalTerminalId": "t-2420009"
  },
  {
    "departureTerminalId": "t-2401401",
    "arrivalTerminalId": "t-2420003"
  },
  {
    "departureTerminalId": "t-2401401",
    "arrivalTerminalId": "t-2839701"
  },
  {
    "departureTerminalId": "t-2401401",
    "arrivalTerminalId": "t-1244901"
  },
  {
    "departureTerminalId": "t-2401401",
    "arrivalTerminalId": "t-1110104"
  },
  {
    "departureTerminalId": "t-2401401",
    "arrivalTerminalId": "t-1118401"
  },
  {
    "departureTerminalId": "t-2401401",
    "arrivalTerminalId": "t-2443501"
  },
  {
    "departureTerminalId": "t-2401401",
    "arrivalTerminalId": "t-2446001"
  },
  {
    "departureTerminalId": "t-2401401",
    "arrivalTerminalId": "t-1244202"
  },
  {
    "departureTerminalId": "t-2401401",
    "arrivalTerminalId": "t-1111501"
  },
  {
    "departureTerminalId": "t-2401401",
    "arrivalTerminalId": "t-1110206"
  },
  {
    "departureTerminalId": "t-2401401",
    "arrivalTerminalId": "t-1114501"
  },
  {
    "departureTerminalId": "t-2401401",
    "arrivalTerminalId": "t-1244501"
  },
  {
    "departureTerminalId": "t-2401401",
    "arrivalTerminalId": "t-1243701"
  },
  {
    "departureTerminalId": "t-2401401",
    "arrivalTerminalId": "t-2420006"
  },
  {
    "departureTerminalId": "t-2401401",
    "arrivalTerminalId": "t-1407701"
  },
  {
    "departureTerminalId": "t-2401401",
    "arrivalTerminalId": "t-1112301"
  }
]